inject_it/__init__.py
inject_it/_checks.py
inject_it/_injector.py
inject_it/decorators.py
inject_it/exceptions.py
inject_it/objects.py
inject_it/register.py
inject_it/stubs.py
inject_it-0.3.2.dist-info/WHEEL
inject_it-0.3.2.dist-info/METADATA
inject_it-0.3.2.dist-info/license_files/LICENSE
inject_it-0.3.2.dist-info/RECORD
