Metadata-Version: 2.1
Name: inject-it
Version: 0.3.2
Summary: Dependency injection done easy using python decorators!
License: MIT
Author-email: Leandro de Souza <leandrodesouzadev@gmail.com>
Requires-Python: >=3.9
Project-URL: Homepage, https://github.com/plathanus-tech/python-inject-it
Project-URL: download_url, https://github.com/plathanus-tech/python-inject-it/releases/tag/v0.3.2
